cross_words-0.0.2.dist-info/DESCRIPTION.rst
cross_words-0.0.2.dist-info/METADATA
cross_words-0.0.2.dist-info/RECORD
cross_words-0.0.2.dist-info/WHEEL
cross_words-0.0.2.dist-info/metadata.json
cross_words-0.0.2.dist-info/top_level.txt
xwords/__init__.py
xwords/core_output.py
xwords/core_parse.py
xwords/core_process.py
xwords/utils.py
xwords/tests/__init__.py
xwords/tests/test_core_output.py
xwords/tests/test_core_parse.py
