Metadata-Version: 2.0
Name: cross-words
Version: 0.0.2
Summary: Chat bot sentences & story generator.
Home-page: https://github.com/data-chirps/xwords
Author: Clément Choukroun, Alexandre Mourachko
Author-email: clement.choukroun@ubisoft.com
License: MIT
Platform: UNKNOWN
Classifier: Programming Language :: Python
Classifier: Development Status :: 1 - Planning
Classifier: Natural Language :: English
Classifier: Operating System :: OS Independent
Classifier: Programming Language :: Python :: 3.6
Classifier: Topic :: Communications
